{
   "identifier": "wishId",
   "label": "description",
   "items": [ { 
        "wishId": 4455, "description": "Don Pepin Garcia Delicias", "size": "7-50", 
        "origin": "Nicaragua", "wrapper": "Corojo", "shape": "Straight"   
      }, {
        "wishId": 4456, "description": "601 Habano Robusto", "size": "5-50", 
        "origin": "Nicaragua", "wrapper": "Natural", "shape": "Straight"   
      }, {
        "wishId": 4457, "description": "Black Pearl Rojo Robusto", "size": "4 3/4-52", 
        "origin": "Nicaragua", "wrapper": "Natural", "shape": "Straight"   
      }, {
        "wishId": 4458, "description": "Padron Churchill", "size": "6 7/8-46", 
        "origin": "Nicaragua", "wrapper": "Natural", "shape": "Straight"   
      }, {
        "wishId": 4459, "description": "Davidoff Aniversario No. 2", "size": "7-48", 
        "origin": "Dominican Republic", "wrapper": "Natural", "shape": "Straight"   
      }, {
        "wishId": 4460, "description": "Cohiba Churchill", "size": "7-49", 
        "origin": "Dominican Republic", "wrapper": "Sungrown", "shape": "Straight"   
      }, {
        "wishId": 4461, "description": "Gurkha Legend Torpedo", "size": "6 3/4-53", 
        "origin": "Honduras", "wrapper": "Colorado Maduro", "shape": "Straight"   
      }, {
        "wishId": 4462, "description": "Cohiba Black Supremo", "size": "6-54", 
        "origin": "Dominican Republic", "wrapper": "Sungrown", "shape": "Straight"   
      }, {
        "wishId": 4463, "description": "La Flor Dominicana Ligero Mysterio", "size": "6 1/8-54", 
        "origin": "Dominican Republic", "wrapper": "Natural", "shape": "Perfecto"   
      }, {
        "wishId": 4464, "description": "Camacho Triple Maduro Torpedo", "size": "6-54", 
        "origin": "Honduras", "wrapper": "Cameroon", "shape": "Torpedo"   
      }
   ]
}
